keras_sig/__init__.py
keras_sig/layer.py
keras_sig/quick_sig.py
keras_sig/signature.py
keras_sig/tensor_ops.py
keras_sig-1.0.2.dist-info/METADATA
keras_sig-1.0.2.dist-info/WHEEL
keras_sig-1.0.2.dist-info/RECORD
