Metadata-Version: 2.1
Name: keras_sig
Version: 1.0.2
Summary: Path Signature in Pure Keras
Author: Rémi Genet
Requires-Python: >=3.9,<3.13
Classifier: Programming Language :: Python :: 3
Classifier: Programming Language :: Python :: 3.9
Classifier: Programming Language :: Python :: 3.10
Classifier: Programming Language :: Python :: 3.11
Classifier: Programming Language :: Python :: 3.12
Requires-Dist: jaxtyping (>=0.2.36,<0.3.0)
Requires-Dist: keras (>=3.0.0,<4.0)
